practice/__init__.py
practice/assignment_star_printer.py
amisha_star-1.0.4.dist-info/METADATA
amisha_star-1.0.4.dist-info/WHEEL
amisha_star-1.0.4.dist-info/top_level.txt
amisha_star-1.0.4.dist-info/RECORD
