Metadata-Version: 2.1
Name: amisha-star
Version: 1.0.4
Summary: A package for printing various star patterns.
Author: Amisha
Author-email: amishaagarwal397@gmail.com
License: MIT
Keywords: printing star pattern
Classifier: Development Status :: 3 - Alpha
Classifier: Intended Audience :: Developers
Classifier: Topic :: Utilities
Classifier: License :: OSI Approved :: MIT License
Classifier: Programming Language :: Python :: 3.12
Requires-Python: >=3.6
